{
  "main": {
    "id": "0c56e80cda158036",
    "type": "split",
    "children": [
      {
        "id": "b78b7d2134a69d53",
        "type": "tabs",
        "children": [
          {
            "id": "a6e537deb7fabc8a",
            "type": "leaf",
            "state": {
              "type": "markdown",
              "state": {
                "file": "obsidian/Extra/PHP/11. Cross Site Scripting XSS/Notes.md",
                "mode": "source",
                "source": false
              }
            }
          }
        ]
      }
    ],
    "direction": "vertical"
  },
  "left": {
    "id": "6b95e3a91d7495cc",
    "type": "split",
    "children": [
      {
        "id": "b79305231e050625",
        "type": "tabs",
        "children": [
          {
            "id": "19752380c3e0b1b0",
            "type": "leaf",
            "state": {
              "type": "file-explorer",
              "state": {
                "sortOrder": "alphabetical"
              }
            }
          },
          {
            "id": "1b7b1694eb8dfdb4",
            "type": "leaf",
            "state": {
              "type": "search",
              "state": {
                "query": "",
                "matchingCase": false,
                "explainSearch": false,
                "collapseAll": false,
                "extraContext": false,
                "sortOrder": "alphabetical"
              }
            }
          },
          {
            "id": "493663f1afc727a2",
            "type": "leaf",
            "state": {
              "type": "bookmarks",
              "state": {}
            }
          }
        ]
      }
    ],
    "direction": "horizontal",
    "width": 200
  },
  "right": {
    "id": "11679b6984b12500",
    "type": "split",
    "children": [
      {
        "id": "02c356e0214d0983",
        "type": "tabs",
        "children": [
          {
            "id": "060aad2af920e6cf",
            "type": "leaf",
            "state": {
              "type": "backlink",
              "state": {
                "file": "obsidian/Extra/PHP/11. Cross Site Scripting XSS/Notes.md",
                "collapseAll": false,
                "extraContext": false,
                "sortOrder": "alphabetical",
                "showSearch": false,
                "searchQuery": "",
                "backlinkCollapsed": false,
                "unlinkedCollapsed": true
              }
            }
          },
          {
            "id": "50ad8a2ee120e386",
            "type": "leaf",
            "state": {
              "type": "outgoing-link",
              "state": {
                "file": "obsidian/Extra/PHP/11. Cross Site Scripting XSS/Notes.md",
                "linksCollapsed": false,
                "unlinkedCollapsed": true
              }
            }
          },
          {
            "id": "759f0a1a71f3e36b",
            "type": "leaf",
            "state": {
              "type": "tag",
              "state": {
                "sortOrder": "frequency",
                "useHierarchy": true
              }
            }
          },
          {
            "id": "802ba0cbb574c6bf",
            "type": "leaf",
            "state": {
              "type": "outline",
              "state": {
                "file": "obsidian/Extra/PHP/11. Cross Site Scripting XSS/Notes.md"
              }
            }
          }
        ],
        "currentTab": 3
      }
    ],
    "direction": "horizontal",
    "width": 200,
    "collapsed": true
  },
  "left-ribbon": {
    "hiddenItems": {
      "switcher:Open quick switcher": false,
      "graph:Open graph view": false,
      "canvas:Create new canvas": false,
      "daily-notes:Open today's daily note": false,
      "templates:Insert template": false,
      "command-palette:Open command palette": false
    }
  },
  "active": "a6e537deb7fabc8a",
  "lastOpenFiles": [
    "obsidian/Kali/Tools/Post Exploitation/CheatSheet.md",
    "obsidian/Extra/PHP/11. Cross Site Scripting XSS/Notes.md",
    "obsidian/Extra/PHP/10. Prepared Statements/Notes.md",
    "obsidian/Extra/PHP/11. Cross Site Scripting XSS",
    "obsidian/Extra/PHP/9. GET SQL Injection/Notes.md",
    "obsidian/Extra/PHP/10. Prepared Statements",
    "obsidian/Extra/PHP/8. Post SQL Injection/Notes.md",
    "obsidian/Extra/PHP/9. GET SQL Injection",
    "obsidian/Extra/PHP/7. Least Privilege/Notes.md",
    "obsidian/Extra/PHP/8. Post SQL Injection",
    "obsidian/Extra/PHP/6. Login Error Messaging/Notes.md",
    "obsidian/Extra/PHP/7. Least Privilege",
    "obsidian/Extra/PHP/5. Refactor the Code/Notes.md",
    "obsidian/Extra/PHP/6. Login Error Messaging",
    "obsidian/Extra/PHP/4. Using Clean URLs/Notes.md",
    "obsidian/Extra/PHP/3. Single Page Loading/Notes.md",
    "obsidian/Extra/PHP/5. Refactor the Code",
    "obsidian/Extra/PHP/4. Using Clean URLs",
    "obsidian/Extra/PHP/2. Secure File Includes/Notes.md",
    "obsidian/Extra/PHP/3. Single Page Loading",
    "obsidian/CTF/Hacker101/CTF/CodyBlog/Notes.md",
    "obsidian/Extra/PHP/1. Keeping Code Private/Notes.md",
    "obsidian/Extra/PHP/2. Secure File Includes",
    "obsidian/CTF/Hacker101/CTF/Micro-CMS-V2/Notes.md",
    "obsidian/Kali/Docs/CTF/CTF Resources.md",
    "obsidian/CTF/TryHackMe/Walkthrough/Wreath/1. Intro/Task 4. Breif/Breif.md",
    "obsidian/CTF/Hacker101/CTF/CodyBlog/IMG/Pasted image 20240908093824.png",
    "obsidian/CTF/Hacker101/CTF/CodyBlog/IMG/Pasted image 20240908085825.png",
    "obsidian/CTF/Hacker101/CTF/CodyBlog/IMG/Pasted image 20240908081732.png",
    "obsidian/CTF/Hacker101/CTF/CodyBlog/IMG/Pasted image 20240908073247.png",
    "obsidian/CTF/Hacker101/CTF/CodyBlog/IMG/Pasted image 20240908072900.png",
    "obsidian/CTF/Hacker101/CTF/TempImage/Notes.md",
    "obsidian/CTF/Hacker101/CTF/CodyBlog/IMG/Pasted image 20240908071807.png",
    "obsidian/CTF/Hacker101/CTF/TempImage/IMG/Pasted image 20240908053220.png",
    "obsidian/CTF/Hacker101/CTF/TempImage/IMG/Pasted image 20240908051941.png",
    "obsidian/CTF/Hacker101/CTF/TempImage/IMG/Pasted image 20240908051546.png",
    "obsidian/CTF/Hacker101/CTF/TempImage/IMG/Pasted image 20240908050743.png",
    "obsidian/Kali/Docs/Concepts/Exploiting Application-Based Vulnerabilities/Exploiting File Inclusion Vulnerabilities/Local File Inclusion Vulnerabilities.md",
    "obsidian/Extra/PortSwigger/File Upload Vulnerabilities/Lab 1/Notes.md",
    "obsidian/CTF/Hacker101/CTF/XSS-Playground/Notes.md",
    "obsidian/CTF/Hacker101/CTF/OSUSEC/Notes.md",
    "obsidian/CTF/Hacker101/CTF/PetShopPro/Notes.md",
    "obsidian/CTF/HTB/Sea/Notes.md",
    "obsidian/CTF/HTB/Sea/Scans.md",
    "obsidian/Extra/PortSwigger/SQL Injection/Overview.md",
    "obsidian/Extra/PortSwigger/SQL Injection/Lab 15./Lab - SQL injection with filter bypass via XML encoding.md"
  ]
}